{
  "generated_at": "2025-11-16T13:02:24.594118+08:00",
  "total_titles_processed": 564,
  "failed_sources": [],
  "trends": [
    {
      "keyword_group": "小学",
      "match_count": 2,
      "titles": [
        {
          "title": "中小学秋假火了亲子游，四川、浙江多景区因游客量饱和限流",
          "url": "https://m.thepaper.cn/newsDetail_forward_31972717",
          "source": "澎湃新闻",
          "ranks": [
            8
          ],
          "is_new": false,
          "appearance_count": 6,
          "time_info": "[08时45分 ~ 13时02分]"
        },
        {
          "title": "去年小学专任教师减少6.62万 ，农村“富余”的老师去哪里",
          "url": "https://news.ifeng.com/c/8oIwdKrJdva",
          "source": "凤凰网",
          "ranks": [
            10
          ],
          "is_new": false,
          "appearance_count": 6,
          "time_info": "[08时45分 ~ 13时02分]"
        }
      ]
    },
    {
      "keyword_group": "谷歌 google gemini",
      "match_count": 1,
      "titles": [
        {
          "title": "巴菲特“退休”前最后一份持仓报告：卖苹果，买谷歌，连续12季度净卖出",
          "url": "https://www.cls.cn/detail/2201480",
          "source": "财联社热门",
          "ranks": [
            3,
            4
          ],
          "is_new": false,
          "appearance_count": 6,
          "time_info": "[08时45分 ~ 13时02分]"
        }
      ]
    }
  ],
  "report_image_url": "https://git.aqde.net/trendradar/img/news.jpg"
}